nds_savecraftr/__init__.py
nds_savecraftr/cli.py
tests/__init__.py
tests/test_converter.py
nds_savecraftr-1.0.0.dist-info/METADATA
nds_savecraftr-1.0.0.dist-info/WHEEL
nds_savecraftr-1.0.0.dist-info/entry_points.txt
nds_savecraftr-1.0.0.dist-info/top_level.txt
nds_savecraftr-1.0.0.dist-info/RECORD
