Metadata-Version: 2.4
Name: nds-savecraftr
Version: 1.0.0
Summary: Universal Nintendo DS Save File Craftr
Home-page: https://github.com/tcsenpai/nds-savecraftr
Author: tcsenpai
Author-email: tcsenpai <tcsenpai@discus.sh>
License: MIT
Project-URL: Homepage, https://github.com/tcsenpai/nds-savecraftr
Project-URL: Repository, https://github.com/tcsenpai/nds-savecraftr
Project-URL: Issues, https://github.com/tcsenpai/nds-savecraftr/issues
Keywords: nintendo,ds,save,converter,twilight,menu,r4,flashcart,craftr
Classifier: Development Status :: 5 - Production/Stable
Classifier: Intended Audience :: End Users/Desktop
Classifier: Topic :: Games/Entertainment
Classifier: Topic :: Utilities
Classifier: License :: OSI Approved :: MIT License
Classifier: Programming Language :: Python :: 3
Classifier: Operating System :: OS Independent
Requires-Python: >=3.7
Dynamic: author
Dynamic: home-page
Dynamic: requires-python
